plantmeter/__init__.py
plantmeter/isodates.py
plantmeter/isodates_test.py
plantmeter/mongotimecurve.py
plantmeter/mongotimecurve_test.py
plantmeter/resource.py
plantmeter/resource_test.py
plantmeter/testutils.py
plantmeter-1.7.12.dist-info/licenses/LICENSE
som_plantmeter/__init__.py
som_plantmeter/__terp__.py
som_plantmeter/erpwrapper.py
som_plantmeter/som_plantmeter.py
plantmeter-1.7.12.dist-info/METADATA
plantmeter-1.7.12.dist-info/WHEEL
plantmeter-1.7.12.dist-info/top_level.txt
plantmeter-1.7.12.dist-info/RECORD
