Metadata-Version: 2.4
Name: plantmeter
Version: 1.7.12
Summary: OpenERP module and library to manage multisite energy generation
Home-page: https://github.com/Som-Energia/plantmeter
Author: Som Energia SCCL
Author-email: info@somenergia.coop
License: GNU General Public License v3 or later (GPLv3+)
Classifier: Programming Language :: Python
Classifier: Programming Language :: Python :: 2.7
Classifier: Programming Language :: Python :: 3
Classifier: Programming Language :: Python :: 3.8
Classifier: Topic :: Software Development :: Libraries :: Python Modules
Classifier: Intended Audience :: Developers
Classifier: Development Status :: 2 - Pre-Alpha
Classifier: License :: OSI Approved :: GNU General Public License v3 or later (GPLv3+)
Classifier: Operating System :: OS Independent
License-File: LICENSE
Requires-Dist: somutils==1.8.9; python_version <= "2.7.18"
Requires-Dist: somutils>1.8.9; python_version > "2.7.18"
Requires-Dist: pymongo==3.13.0; python_version <= "2.7.18"
Requires-Dist: pymongo<4.0; python_version > "2.7.18"
Requires-Dist: numpy<1.17; python_version <= "2.7.18"
Requires-Dist: numpy; python_version > "2.7.18"
Requires-Dist: xlrd
Requires-Dist: yamlns
Dynamic: author
Dynamic: author-email
Dynamic: classifier
Dynamic: description
Dynamic: description-content-type
Dynamic: home-page
Dynamic: license
Dynamic: license-file
Dynamic: requires-dist
Dynamic: summary
